all_charts_component/__init__.py
all_charts_component/example.py
all_charts_component/frontend/build/asset-manifest.json
all_charts_component/frontend/build/bootstrap.min.css
all_charts_component/frontend/build/bootstrap.min.css.map
all_charts_component/frontend/build/index.html
all_charts_component/frontend/build/static/css/main.112a5be0.css
all_charts_component/frontend/build/static/css/main.112a5be0.css.map
all_charts_component/frontend/build/static/js/main.34da4ad7.js
all_charts_component/frontend/build/static/js/main.34da4ad7.js.LICENSE.txt
all_charts_component/frontend/build/static/js/main.34da4ad7.js.map
streamlit_nivo_charts_custom-0.0.15.dist-info/LICENSE
streamlit_nivo_charts_custom-0.0.15.dist-info/METADATA
streamlit_nivo_charts_custom-0.0.15.dist-info/WHEEL
streamlit_nivo_charts_custom-0.0.15.dist-info/top_level.txt
streamlit_nivo_charts_custom-0.0.15.dist-info/RECORD
